openg2p_fastapi_auth/__init__.py
openg2p_fastapi_auth/app.py
openg2p_fastapi_auth/config.py
openg2p_fastapi_auth/context.py
openg2p_fastapi_auth/dependencies.py
openg2p_fastapi_auth/auth/__init__.py
openg2p_fastapi_auth/auth/factory/__init__.py
openg2p_fastapi_auth/auth/factory/factory.py
openg2p_fastapi_auth/auth/implementations/__init__.py
openg2p_fastapi_auth/auth/implementations/beneficiary_esignet.py
openg2p_fastapi_auth/auth/implementations/beneficiary_keycloak.py
openg2p_fastapi_auth/auth/implementations/staff_keycloak.py
openg2p_fastapi_auth/auth/interface/__init__.py
openg2p_fastapi_auth/auth/interface/interface.py
openg2p_fastapi_auth-1.1.4.dist-info/METADATA
openg2p_fastapi_auth-1.1.4.dist-info/WHEEL
openg2p_fastapi_auth-1.1.4.dist-info/licenses/LICENSE
openg2p_fastapi_auth-1.1.4.dist-info/RECORD
