Metadata-Version: 2.4
Name: openg2p-fastapi-auth
Version: 1.1.4
Summary: OpenG2P Library for initializing authn and authz for defined APIs
Project-URL: Homepage, https://openg2p.org
Project-URL: Documentation, https://docs.openg2p.org/
Project-URL: Repository, https://github.com/openg2p/openg2p-fastapi-common
Author-email: OpenG2P <info@openg2p.org>
License-File: LICENSE
Classifier: License :: OSI Approved :: Mozilla Public License 2.0 (MPL 2.0)
Classifier: Operating System :: OS Independent
Classifier: Programming Language :: Python :: 3
Requires-Python: >=3.7
Requires-Dist: cryptography>=41.0.4
Requires-Dist: openg2p-fastapi-auth-models
Requires-Dist: openg2p-fastapi-common
Requires-Dist: python-jose>=3.3.0
